MANIFEST.in
README.md
setup.cfg
setup.py
mt_mafka.egg-info/PKG-INFO
mt_mafka.egg-info/SOURCES.txt
mt_mafka.egg-info/dependency_links.txt
mt_mafka.egg-info/entry_points.txt
mt_mafka.egg-info/not-zip-safe
mt_mafka.egg-info/requires.txt
mt_mafka.egg-info/top_level.txt
pysparkcli/__init__.py
pysparkcli/bin/__init__.py
pysparkcli/bin/start.py
pysparkcli/core/__init__.py
pysparkcli/core/admin/__init__.py
pysparkcli/core/conf/__init__.py
pysparkcli/core/conf/base.py
pysparkcli/core/utils/__init__.py
pysparkcli/core/utils/handle_zip_files.py
pysparkcli/project-template/default/project_name/src/__init__.py-tpl
pysparkcli/project-template/default/project_name/src/app.py-tpl
pysparkcli/project-template/default/project_name/src/configs/__init__.py-tpl
pysparkcli/project-template/default/project_name/src/configs/etl_config.json
pysparkcli/project-template/default/project_name/src/jobs/__init__.py-tpl
pysparkcli/project-template/default/project_name/src/jobs/etl_job.py-tpl
pysparkcli/project-template/default/project_name/src/settings/__init__.py-tpl
pysparkcli/project-template/default/project_name/src/settings/default.py-tpl
pysparkcli/project-template/default/project_name/src/settings/local.py-tpl
pysparkcli/project-template/default/project_name/src/settings/production.py-tpl
pysparkcli/project-template/default/project_name/tests/__init__.py
pysparkcli/project-template/default/project_name/tests/test_etl_job.py
pysparkcli/project-template/default/project_name/tests/test_data/employees/part-00000-9abf32a3-db43-42e1-9639-363ef11c0d1c-c000.snappy.parquet
pysparkcli/project-template/default/project_name/tests/test_data/employees_report/part-00000-4a609ba3-0404-48bb-bb22-2fec3e2f1e68-c000.snappy.parquet
pysparkcli/project-template/streaming/project_name/__init__.py-tpl
pysparkcli/project-template/streaming/project_name/requirements.txt
pysparkcli/project-template/streaming/project_name/src/__init__.py-tpl
pysparkcli/project-template/streaming/project_name/src/app.py-tpl
pysparkcli/project-template/streaming/project_name/src/configs/__init__.py-tpl
pysparkcli/project-template/streaming/project_name/src/configs/spark_config.py-tpl
