Metadata-Version: 2.1
Name: mt-mafka
Version: 2.5.0
Home-page: https://github.com/mtdev/mtkafka
Author: mtdev
Author-email: wuuuuusmall@outlook.com
License: MIT
Requires-Dist: click
Requires-Dist: jinja2
Requires-Dist: pathlib>1.0.0
